LICENSE
MANIFEST.in
setup.cfg
setup.py
xcodetool/__init__.py
xcodetool/__main__.py
xcodetool/xcodetool.py
xcodetool.egg-info/PKG-INFO
xcodetool.egg-info/SOURCES.txt
xcodetool.egg-info/dependency_links.txt
xcodetool.egg-info/entry_points.txt
xcodetool.egg-info/top_level.txt
xcodetool/options/ad-hoc.plist
xcodetool/options/app-store.plist
xcodetool/options/enterprise.plist