Metadata-Version: 1.2
Name: xcodetool
Version: 0.0.1
Summary: A convenient python tool for xcodebuild
Home-page: https://github.com/canius/xcodetool
Author: Canius Chu
Author-email: canius.chu@outlook.com
License: MIT
Download-URL: https://github.com/canius/xcodetool/archive/0.0.1.tar.gz
Keywords: ios,xcode,build,xcodebuild,jenkins
Platform: UNKNOWN
Requires-Python: >=2.7
